uni_legacy/__init__.py
Uni_Legacy-1.0.0.dist-info/METADATA
Uni_Legacy-1.0.0.dist-info/WHEEL
Uni_Legacy-1.0.0.dist-info/top_level.txt
Uni_Legacy-1.0.0.dist-info/RECORD
