Metadata-Version: 2.1
Name: Uni-Legacy
Version: 1.0.0
Summary: A simple python library for convert sinhala unicode font to legacy font. Supported for FM fonts and Isi fonts.This library can be used offline
Home-page: 
Author: Gavindu Tharaka
Author-email: gavi.tharaka@gmail.com
License: UNKNOWN
Platform: UNKNOWN
Classifier: Programming Language :: Python :: 3
Classifier: License :: OSI Approved :: MIT License
Classifier: Operating System :: OS Independent
Requires-Python: >=3.6
